pottsshrinkage/__init__.py
pottsshrinkage/completeshrinkage.py
pottscompleteshrinkage-1.0.14.dist-info/METADATA
pottscompleteshrinkage-1.0.14.dist-info/WHEEL
pottscompleteshrinkage-1.0.14.dist-info/entry_points.txt
pottscompleteshrinkage-1.0.14.dist-info/top_level.txt
pottscompleteshrinkage-1.0.14.dist-info/RECORD
