Metadata-Version: 2.1
Name: pottscompleteshrinkage
Version: 1.0.14
Summary: Potts Clustering with Complete Shrinkage
Home-page: https://github.com/kgalahassa/pottscompleteshrinkage
Author: Alejandro, Murua and Alahassa, Nonvikan Karl-Augustt
Author-email: alahassa@dms.umontreal.ca
License: GNU General Public License v3.0
Keywords: Potts models,Clustering,Complete Shrinkage
Platform: UNKNOWN
Classifier: Programming Language :: Python :: 3
Classifier: License :: OSI Approved :: GNU Lesser General Public License v3 (LGPLv3)
Classifier: Operating System :: OS Independent
Requires-Dist: numpy (==1.20.2)
Requires-Dist: pandas (==1.2.4)
Requires-Dist: scikit-learn (==0.24.2)
